hqde/__init__.py
hqde/__main__.py
hqde/py.typed
hqde/core/__init__.py
hqde/core/hqde_system.py
hqde/distributed/__init__.py
hqde/distributed/fault_tolerance.py
hqde/distributed/hierarchical_aggregator.py
hqde/distributed/load_balancer.py
hqde/distributed/mapreduce_ensemble.py
hqde/quantum/__init__.py
hqde/quantum/quantum_aggregator.py
hqde/quantum/quantum_noise.py
hqde/quantum/quantum_optimization.py
hqde/utils/__init__.py
hqde/utils/config_manager.py
hqde/utils/data_utils.py
hqde/utils/performance_monitor.py
hqde/utils/visualization.py
hqde-0.1.4.dist-info/licenses/LICENSE
hqde-0.1.4.dist-info/METADATA
hqde-0.1.4.dist-info/WHEEL
hqde-0.1.4.dist-info/top_level.txt
hqde-0.1.4.dist-info/RECORD
