Metadata-Version: 2.4
Name: hqde
Version: 0.1.4
Summary: Hierarchical Quantum-Distributed Ensemble Learning Framework
Author-email: HQDE Team <hqde@example.com>
Maintainer-email: HQDE Team <hqde@example.com>
License: MIT
Project-URL: Homepage, https://github.com/Prathmesh333/Hierarchical-Quantum-Distributed-Ensemble-Learning
Project-URL: Repository, https://github.com/Prathmesh333/Hierarchical-Quantum-Distributed-Ensemble-Learning
Project-URL: Documentation, https://github.com/Prathmesh333/Hierarchical-Quantum-Distributed-Ensemble-Learning/blob/main/HOW_TO_RUN.md
Project-URL: Bug Reports, https://github.com/Prathmesh333/Hierarchical-Quantum-Distributed-Ensemble-Learning/issues
Keywords: machine-learning,quantum,distributed,ensemble,deep-learning,pytorch,ray
Classifier: Development Status :: 4 - Beta
Classifier: Intended Audience :: Science/Research
Classifier: Intended Audience :: Developers
Classifier: License :: OSI Approved :: MIT License
Classifier: Operating System :: OS Independent
Classifier: Programming Language :: Python :: 3
Classifier: Programming Language :: Python :: 3.9
Classifier: Programming Language :: Python :: 3.10
Classifier: Programming Language :: Python :: 3.11
Classifier: Programming Language :: Python :: 3.12
Classifier: Topic :: Scientific/Engineering :: Artificial Intelligence
Classifier: Topic :: Software Development :: Libraries :: Python Modules
Requires-Python: >=3.9
License-File: LICENSE
Requires-Dist: numpy>=2.0.2
Requires-Dist: torch>=2.8.0
Requires-Dist: torchvision>=0.23.0
Requires-Dist: ray[default]>=2.49.2
Requires-Dist: scikit-learn>=1.6.1
Requires-Dist: psutil>=7.1.0
Provides-Extra: dev
Requires-Dist: pytest>=8.4.2; extra == "dev"
Requires-Dist: ipython>=8.18.1; extra == "dev"
Requires-Dist: matplotlib>=3.9.4; extra == "dev"
Requires-Dist: pandas>=2.3.2; extra == "dev"
Requires-Dist: seaborn>=0.13.2; extra == "dev"
Requires-Dist: tqdm>=4.67.1; extra == "dev"
Dynamic: license-file
